google/cloud/sql/connector/__init__.py
google/cloud/sql/connector/asyncpg.py
google/cloud/sql/connector/client.py
google/cloud/sql/connector/connection_info.py
google/cloud/sql/connector/connection_name.py
google/cloud/sql/connector/connector.py
google/cloud/sql/connector/enums.py
google/cloud/sql/connector/exceptions.py
google/cloud/sql/connector/instance.py
google/cloud/sql/connector/lazy.py
google/cloud/sql/connector/pg8000.py
google/cloud/sql/connector/py.typed
google/cloud/sql/connector/pymysql.py
google/cloud/sql/connector/pytds.py
google/cloud/sql/connector/rate_limiter.py
google/cloud/sql/connector/refresh_utils.py
google/cloud/sql/connector/resolver.py
google/cloud/sql/connector/utils.py
google/cloud/sql/connector/version.py
cloud_sql_python_connector-1.16.0.dist-info/LICENSE
cloud_sql_python_connector-1.16.0.dist-info/METADATA
cloud_sql_python_connector-1.16.0.dist-info/WHEEL
cloud_sql_python_connector-1.16.0.dist-info/top_level.txt
cloud_sql_python_connector-1.16.0.dist-info/RECORD
