Metadata-Version: 2.1
Name: cloud-sql-python-connector
Version: 1.16.0
Summary: The Cloud SQL Python Connector is a library that can be used alongside a database driver to allow users with sufficient permissions to connect to a Cloud SQL database without having to manually allowlist IPs or manage SSL certificates.
Home-page: https://github.com/GoogleCloudPlatform/cloud-sql-python-connector
Author: Google LLC
Author-email: googleapis-packages@google.com
License: Apache 2.0
Platform: Posix; MacOS X; Windows
Classifier: Development Status :: 5 - Production/Stable
Classifier: Intended Audience :: Developers
Classifier: License :: OSI Approved :: Apache Software License
Classifier: Programming Language :: Python
Classifier: Programming Language :: Python :: 3.9
Classifier: Programming Language :: Python :: 3.10
Classifier: Programming Language :: Python :: 3.11
Classifier: Programming Language :: Python :: 3.12
Classifier: Programming Language :: Python :: 3.13
Requires-Python: >=3.9
License-File: LICENSE
Requires-Dist: aiofiles
Requires-Dist: aiohttp
Requires-Dist: cryptography>=42.0.0
Requires-Dist: dnspython>=2.0.0
Requires-Dist: Requests
Requires-Dist: google-auth>=2.28.0
Provides-Extra: pymysql
Requires-Dist: PyMySQL>=1.1.0; extra == "pymysql"
Provides-Extra: pg8000
Requires-Dist: pg8000>=1.31.1; extra == "pg8000"
Provides-Extra: pytds
Requires-Dist: python-tds>=1.15.0; extra == "pytds"
Provides-Extra: asyncpg
Requires-Dist: asyncpg>=0.30.0; extra == "asyncpg"
